precise/__init__.py
precise/whereami.py
precise/inclusion/__init__.py
precise/inclusion/matplotlibinclusion.py
precise/inclusion/pyportfoliooptinclusion.py
precise/inclusion/riskfoliolibinclusion.py
precise/inclusion/riskparityportfolioinclusion.py
precise/inclusion/runthisinclusion.py
precise/skaters/__init__.py
precise/skaters/exceptions.py
precise/skaters/covariance/__init__.py
precise/skaters/covariance/allcovskaters.py
precise/skaters/covariance/avgfactory.py
precise/skaters/covariance/avgtop.py
precise/skaters/covariance/bufemp.py
precise/skaters/covariance/bufempfactory.py
precise/skaters/covariance/buffactory.py
precise/skaters/covariance/bufhuber.py
precise/skaters/covariance/bufhuberfactory.py
precise/skaters/covariance/bufsk.py
precise/skaters/covariance/bufskfactory.py
precise/skaters/covariance/ewaemp.py
precise/skaters/covariance/ewaempfactory.py
precise/skaters/covariance/ewalw.py
precise/skaters/covariance/ewalwfactory.py
precise/skaters/covariance/ewalz.py
precise/skaters/covariance/ewalzfactory.py
precise/skaters/covariance/ewapm.py
precise/skaters/covariance/ewapmfactory.py
precise/skaters/covariance/identity.py
precise/skaters/covariance/runemp.py
precise/skaters/covariance/runempfactory.py
precise/skaters/covariance/weakboot.py
precise/skaters/covariance/weakewa.py
precise/skaters/covariance/weakfactory.py
precise/skaters/covariance/weaklz.py
precise/skaters/covariance/weakpm.py
precise/skaters/covariance/weaksk.py
precise/skaters/covarianceutil/__init__.py
precise/skaters/covarianceutil/adjacency.py
precise/skaters/covarianceutil/conventions.py
precise/skaters/covarianceutil/covdecomposition.py
precise/skaters/covarianceutil/covfunctions.py
precise/skaters/covarianceutil/covrandom.py
precise/skaters/covarianceutil/datafunctions.py
precise/skaters/covarianceutil/datascatterfunctions.py
precise/skaters/covarianceutil/differencing.py
precise/skaters/covarianceutil/hubercov.py
precise/skaters/covarianceutil/likelihood.py
precise-0.16.7.dist-info/LICENSE
precise-0.16.7.dist-info/METADATA
precise-0.16.7.dist-info/WHEEL
precise-0.16.7.dist-info/entry_points.txt
precise-0.16.7.dist-info/top_level.txt
precise-0.16.7.dist-info/RECORD
