Metadata-Version: 2.1
Name: precise
Version: 0.16.7
Summary: The home of Schur Hierarchical Portfolios: an aesthetically pleasing version of Hierarchical Risk Parity
Home-page: https://github.com/microprediction/precise
Author: microprediction
Author-email: peter.cotton@microprediction.com
License: MIT
Classifier: License :: OSI Approved :: MIT License
Classifier: Programming Language :: Python :: 3
Classifier: Programming Language :: Python :: 3.8
License-File: LICENSE
Requires-Dist: numpy
Requires-Dist: momentum>=0.2.7
Requires-Dist: kmeans1d
Requires-Dist: scikit-learn
Requires-Dist: latextable
Requires-Dist: tomark
Requires-Dist: pandas-datareader
Requires-Dist: pandas
Requires-Dist: scipy
Requires-Dist: pyportfolioopt
Requires-Dist: collinearity
Requires-Dist: yfinance
Requires-Dist: dictionaries
